dm_core/__init__.py
dm_core/migrationcd/__init__.py
dm_core/migrationcd/abc.py
dm_core/migrationcd/apps.py
dm_core/migrationcd/models.py
dm_core/migrationcd/management/__init__.py
dm_core/migrationcd/management/commands/__init__.py
dm_core/migrationcd/management/commands/migratecd.py
dm_core/migrationcd/migrations/0001_initial.py
dm_core/migrationcd/migrations/__init__.py
dm_core/migrationcd/tests/__init__.py
dm_core_migrationcd-1.0.1.dist-info/licenses/LICENSE
dm_core_migrationcd-1.0.1.dist-info/METADATA
dm_core_migrationcd-1.0.1.dist-info/WHEEL
dm_core_migrationcd-1.0.1.dist-info/top_level.txt
dm_core_migrationcd-1.0.1.dist-info/RECORD
